lslock/__init__.py
lslock/exceptions/__init__.py
lslock/functions/LsLock.py
lslock/functions/LsLockClient.py
lslock/functions/__init__.py
lslock/pydantic_models/TLock.py
lslock/pydantic_models/__init__.py
lslock/server/__init__.py
lslock/server/functions/LsLockServer.py
lslock/server/functions/__init__.py
lslock-3.0.2.dist-info/METADATA
lslock-3.0.2.dist-info/WHEEL
lslock-3.0.2.dist-info/entry_points.txt
lslock-3.0.2.dist-info/RECORD
