Metadata-Version: 2.1
Name: lslock
Version: 3.0.2
Summary: resource locking system
Author: IT
Author-email: it@electronic-shop.lu
Requires-Python: >=3.11,<4.0
Classifier: Programming Language :: Python :: 3
Classifier: Programming Language :: Python :: 3.11
Provides-Extra: server
Requires-Dist: am-auth-functions (>=5.0.10,<6.0.0) ; extra == "server"
Requires-Dist: lscentrallog (>=3.0.8,<4.0.0) ; extra == "server"
Requires-Dist: lsexceptions (>=1.0.1,<2.0.0)
Requires-Dist: lsfastapi (>=4.1.4,<5.0.0) ; extra == "server"
Requires-Dist: lsidentity (>=1.0.0,<2.0.0)
Requires-Dist: lsmeta-pydantic (>=1.0.1,<2.0.0)
Requires-Dist: lsrestclient (>=1.7.2,<2.0.0)
Requires-Dist: lstools (>=3.2.1,<4.0.0)
Requires-Dist: supervisor (>=4.2.5,<5.0.0)
